{
  "fetched_at": "2026-01-15T21:04:32.293396Z",
  "source": "https://www.quiverquant.com/strategies/",
  "n_strategies": 31,
  "n_errors": 0,
  "errors": [],
  "strategies": {
    "Analyst Buys": {
      "start_date": "2023-02-01",
      "return_1d": "0.23%",
      "return_30d": "-2.35%",
      "return_1y": "11.40%",
      "cagr": "27.88%",
      "max_drawdown": "-26.10%",
      "beta": 1.24,
      "alpha": 0.03,
      "sharpe": 0.81,
      "win_rate": "80.38%",
      "avg_win": "0.61%",
      "avg_loss": "-0.72%",
      "volatility": "3.11%",
      "std_dev": 0.18,
      "info_ratio": 0.56,
      "treynor": 0.12,
      "trades": 336,
      "description": "The Analyst Buys Strategy uses Quiver’s proprietary Analyst Scoring method, which rates Wall Street Analysts based on the accuracy of their historical price targets. We use these scores to weight each analyst’s most recent forecasts, giving a stronger weight to analysts with historical success, and lower (or in some cases, negative) weights to analysts with poor historical accuracy. We then take all forecasts made over the last year, and find the average weighted forecast for every ticker. We take the stocks with the top 100 scores, and then narrow it down to the top 10 largest by market cap (to avoid stocks with sparse analyst coverage). The strategy takes an equal-weighted position in those 10 companies, and rebalances on a monthly basis.",
      "source_url": "https://www.quiverquant.com/strategies/s/Analyst Buys/"
    },
    "Bill Ackman": {
      "start_date": "2015-02-18",
      "return_1d": "-0.25%",
      "return_30d": "3.40%",
      "return_1y": "8.83%",
      "cagr": "16.96%",
      "max_drawdown": "-45.10%",
      "beta": 0.97,
      "alpha": 0.03,
      "sharpe": 0.614,
      "win_rate": "73.76%",
      "avg_win": "0.74%",
      "avg_loss": "-0.49%",
      "volatility": "2.84%",
      "std_dev": 0.17,
      "info_ratio": 0.29,
      "treynor": 0.11,
      "trades": 737,
      "description": "The Bill Ackman Strategy attempts to mirror the portfolio of Bill Ackman's Pershing Square Capital Management using 13F filings and is rebalanced when new filings are reported.",
      "source_url": "https://www.quiverquant.com/strategies/s/Bill Ackman/"
    },
    "Bill Gates": {
      "start_date": "2015-02-17",
      "return_1d": "0.32%",
      "return_30d": "0.70%",
      "return_1y": "16.58%",
      "cagr": "13.51%",
      "max_drawdown": "-33.20%",
      "beta": 0.86,
      "alpha": 0.01,
      "sharpe": 0.52,
      "win_rate": "65.78%",
      "avg_win": "0.49%",
      "avg_loss": "-0.29%",
      "volatility": "2.27%",
      "std_dev": 0.15,
      "info_ratio": 0.01,
      "treynor": 0.09,
      "trades": 1051,
      "description": "The Bill Gates Strategy attempts to mirror the portfolio of Bill Gates's Bill & Melinda Gates Foundation Trust using 13F filings and is rebalanced when new filings are reported.",
      "source_url": "https://www.quiverquant.com/strategies/s/Bill Gates/"
    },
    "Cleo Fields": {
      "start_date": "2025-06-30",
      "return_1d": "1.08%",
      "return_30d": "4.29%",
      "return_1y": "21.61%",
      "cagr": "40.64%",
      "max_drawdown": "-12.40%",
      "beta": 1.59,
      "alpha": 0.06,
      "sharpe": 1.287,
      "win_rate": "74.80%",
      "avg_win": "0.05%",
      "avg_loss": "-0.02%",
      "volatility": "3.26%",
      "std_dev": 0.18,
      "info_ratio": 0.98,
      "treynor": 0.15,
      "trades": 200,
      "description": "The Cleo Fields Strategy attempts to mirror the portfolio of common stock for Rep. Cleo Fields (and their family) and is rebalanced when new trades or annual reports are reported.",
      "source_url": "https://www.quiverquant.com/strategies/s/Cleo Fields/"
    },
    "Congress Buys": {
      "start_date": "2020-04-01",
      "return_1d": "0.24%",
      "return_30d": "0.91%",
      "return_1y": "32.69%",
      "cagr": "35.13%",
      "max_drawdown": "-22.80%",
      "beta": 1.12,
      "alpha": 0.09,
      "sharpe": 1.059,
      "win_rate": "64.11%",
      "avg_win": "0.35%",
      "avg_loss": "-0.25%",
      "volatility": "4.62%",
      "std_dev": 0.21,
      "info_ratio": 0.76,
      "treynor": 0.2,
      "trades": 2914,
      "description": "The Congress Buys Strategy tracks the performance of stocks that have been purchased by members of U.S. Congress (or their family). This strategy is weighted based on the reported size of the purchases, with weekly rebalancing.",
      "source_url": "https://www.quiverquant.com/strategies/s/Congress Buys/"
    },
    "Congress Long-Short": {
      "start_date": "2020-04-01",
      "return_1d": "0.30%",
      "return_30d": "1.70%",
      "return_1y": "34.02%",
      "cagr": "32.29%",
      "max_drawdown": "-24.60%",
      "beta": 1.12,
      "alpha": 0.08,
      "sharpe": 0.904,
      "win_rate": "51.52%",
      "avg_win": "0.31%",
      "avg_loss": "-0.19%",
      "volatility": "5.71%",
      "std_dev": 0.24,
      "info_ratio": 0.54,
      "treynor": 0.19,
      "trades": 5334,
      "description": "The Congress Long-Short Strategy tracks the performance of stocks that have been purchased or sold by members of U.S. Congress (or their family). It takes a long position in stocks that have been purchased, and a short position in stocks which have been sold. This strategy is weighted based on the reported size of the transactions and employs leverage with 130% long exposure and 30% short exposure, with weekly rebalancing.",
      "source_url": "https://www.quiverquant.com/strategies/s/Congress Long-Short/"
    },
    "Congress Sells": {
      "start_date": "2020-04-01",
      "return_1d": "0.61%",
      "return_30d": "-0.83%",
      "return_1y": "-0.18%",
      "cagr": "22.46%",
      "max_drawdown": "-26.40%",
      "beta": 1.06,
      "alpha": 0.01,
      "sharpe": 0.724,
      "win_rate": "62.42%",
      "avg_win": "0.29%",
      "avg_loss": "-0.25%",
      "volatility": "3.71%",
      "std_dev": 0.19,
      "info_ratio": 0.15,
      "treynor": 0.13,
      "trades": 2856,
      "description": "The Congress Sells Strategy tracks the performance of stocks that have been sold by members of U.S. Congress (or their family). It takes a long position in stocks that have been sold. This strategy is weighted based on the reported size of the transactions, with weekly rebalancing.",
      "source_url": "https://www.quiverquant.com/strategies/s/Congress Sells/"
    },
    "Dan Meuser": {
      "start_date": "2019-08-14",
      "return_1d": "1.57%",
      "return_30d": "3.78%",
      "return_1y": "31.81%",
      "cagr": "38.58%",
      "max_drawdown": "-43.30%",
      "beta": 1.29,
      "alpha": 0.14,
      "sharpe": 1.037,
      "win_rate": "74.00%",
      "avg_win": "1.24%",
      "avg_loss": "-0.17%",
      "volatility": "6.53%",
      "std_dev": 0.26,
      "info_ratio": 1.17,
      "treynor": 0.21,
      "trades": 492,
      "description": "The Dan Meuser Strategy attempts to mirror the portfolio of common stock for Rep. Dan Meuser (and their family) and is rebalanced when new trades or annual reports are reported.",
      "source_url": "https://www.quiverquant.com/strategies/s/Dan Meuser/"
    },
    "Donald Beyer": {
      "start_date": "2016-05-09",
      "return_1d": "0.17%",
      "return_30d": "1.76%",
      "return_1y": "18.48%",
      "cagr": "20.07%",
      "max_drawdown": "-32.50%",
      "beta": 0.99,
      "alpha": 0.04,
      "sharpe": 0.728,
      "win_rate": "77.95%",
      "avg_win": "0.33%",
      "avg_loss": "-0.13%",
      "volatility": "2.89%",
      "std_dev": 0.17,
      "info_ratio": 0.43,
      "treynor": 0.13,
      "trades": 1188,
      "description": "The Donald Beyer Strategy attempts to mirror the portfolio of common stock for Rep. Don Beyer (and their family) and is rebalanced when new trades or annual reports are reported.",
      "source_url": "https://www.quiverquant.com/strategies/s/Donald Beyer/"
    },
    "Energy and Commerce Committee (House)": {
      "start_date": "2020-04-01",
      "return_1d": "0.38%",
      "return_30d": "-1.87%",
      "return_1y": "14.59%",
      "cagr": "19.14%",
      "max_drawdown": "-39.90%",
      "beta": 0.85,
      "alpha": 0.01,
      "sharpe": 0.605,
      "win_rate": "69.43%",
      "avg_win": "0.48%",
      "avg_loss": "-0.55%",
      "volatility": "3.83%",
      "std_dev": 0.2,
      "info_ratio": -0.02,
      "treynor": 0.14,
      "trades": 1457,
      "description": "The Energy and Commerce Committee (House) Strategy tracks the performance of stocks that have been recently purchased by current/past members of the U.S. House's Energy and Commerce Committee (or their family). This strategy is weighted based on the reported size of the purchases, with weekly rebalancing.",
      "source_url": "https://www.quiverquant.com/strategies/s/Energy and Commerce Committee (House)/"
    },
    "Homeland Security Committee (Senate)": {
      "start_date": "2020-04-01",
      "return_1d": "-0.46%",
      "return_30d": "3.72%",
      "return_1y": "8.45%",
      "cagr": "12.32%",
      "max_drawdown": "-32.90%",
      "beta": 0.44,
      "alpha": 0.02,
      "sharpe": 0.384,
      "win_rate": "69.67%",
      "avg_win": "0.33%",
      "avg_loss": "-0.45%",
      "volatility": "3.21%",
      "std_dev": 0.18,
      "info_ratio": -0.29,
      "treynor": 0.16,
      "trades": 1552,
      "description": "The Homeland Security Committee (Senate) Strategy tracks the performance of stocks that have been recently purchased by current/past members of the U.S. Senate's Homeland Security Committee (or their family). This strategy is weighted based on the reported size of the purchases, with weekly rebalancing.",
      "source_url": "https://www.quiverquant.com/strategies/s/Homeland Security Committee (Senate)/"
    },
    "Howard Marks": {
      "start_date": "2015-02-17",
      "return_1d": "0.21%",
      "return_30d": "7.93%",
      "return_1y": "39.68%",
      "cagr": "15.81%",
      "max_drawdown": "-45.50%",
      "beta": 0.87,
      "alpha": 0.03,
      "sharpe": 0.54,
      "win_rate": "66.17%",
      "avg_win": "0.54%",
      "avg_loss": "-0.35%",
      "volatility": "3.52%",
      "std_dev": 0.19,
      "info_ratio": 0.17,
      "treynor": 0.12,
      "trades": 1125,
      "description": "The Howard Marks Strategy attempts to mirror the portfolio of Howard Marks's Oaktree Capital Management using 13F filings and is rebalanced when new filings are reported.",
      "source_url": "https://www.quiverquant.com/strategies/s/Howard Marks/"
    },
    "Insider Purchases": {
      "start_date": "2014-01-01",
      "return_1d": "1.94%",
      "return_30d": "12.99%",
      "return_1y": "12.73%",
      "cagr": "18.67%",
      "max_drawdown": "-52.90%",
      "beta": 0.91,
      "alpha": 0.07,
      "sharpe": 0.54,
      "win_rate": "60.89%",
      "avg_win": "0.43%",
      "avg_loss": "-0.52%",
      "volatility": "6.71%",
      "std_dev": 0.26,
      "info_ratio": 0.27,
      "treynor": 0.15,
      "trades": 7483,
      "description": "The Insider Purchases Strategy uses a proprietary model to score purchases made by Insiders within companies based on factors related to the trade, the insider, and the company. Scores are then rolled up to a company level based on a decaying trailing window, where the top 10 companies are equally weighted at the start of every week. The writeup on the methodology of this strategy can be found here .",
      "source_url": "https://www.quiverquant.com/strategies/s/Insider Purchases/"
    },
    "Inverse CNBC": {
      "start_date": "2021-01-01",
      "return_1d": "0.07%",
      "return_30d": "-1.39%",
      "return_1y": "-7.92%",
      "cagr": "-3.77%",
      "max_drawdown": "-47.80%",
      "beta": -0.32,
      "alpha": -0.03,
      "sharpe": -0.528,
      "win_rate": "36.96%",
      "avg_win": "0.42%",
      "avg_loss": "-0.30%",
      "volatility": "1.18%",
      "std_dev": 0.11,
      "info_ratio": -0.61,
      "treynor": 0.18,
      "trades": 2135,
      "description": "The Inverse CNBC Strategy takes a short position in CNBC's 10 most-recommended tickers (whether bullish or bearish) over the previous 90 days, and hedges it with a long position in the market index. It rebalances on a weekly basis, with equal weighting.",
      "source_url": "https://www.quiverquant.com/strategies/s/Inverse CNBC/"
    },
    "Inverse Cramer": {
      "start_date": "2021-01-01",
      "return_1d": "0.22%",
      "return_30d": "1.37%",
      "return_1y": "-21.93%",
      "cagr": "1.21%",
      "max_drawdown": "-46.30%",
      "beta": -0.24,
      "alpha": 0.0,
      "sharpe": -0.11,
      "win_rate": "43.13%",
      "avg_win": "0.60%",
      "avg_loss": "-0.47%",
      "volatility": "2.31%",
      "std_dev": 0.15,
      "info_ratio": -0.39,
      "treynor": 0.07,
      "trades": 3161,
      "description": "The Inverse Cramer Strategy takes a short position in Cramer's 10 most-recommended tickers (whether bullish or bearish) over the previous 30 days, and hedges it with a long position in the market index. It rebalances on a weekly basis, with equal weighting.",
      "source_url": "https://www.quiverquant.com/strategies/s/Inverse Cramer/"
    },
    "Josh Gottheimer": {
      "start_date": "2019-01-01",
      "return_1d": "-0.40%",
      "return_30d": "-2.54%",
      "return_1y": "11.15%",
      "cagr": "21.11%",
      "max_drawdown": "-33.70%",
      "beta": 1.1,
      "alpha": 0.02,
      "sharpe": 0.652,
      "win_rate": "87.23%",
      "avg_win": "0.08%",
      "avg_loss": "-0.03%",
      "volatility": "4.29%",
      "std_dev": 0.21,
      "info_ratio": 0.34,
      "treynor": 0.12,
      "trades": 3091,
      "description": "The Josh Gottheimer Strategy attempts to mirror the portfolio of common stock for Rep. Josh Gottheimer (and their family) and is rebalanced when new trades or annual reports are reported.",
      "source_url": "https://www.quiverquant.com/strategies/s/Josh Gottheimer/"
    },
    "Lobbying Spending Growth": {
      "start_date": "2009-03-01",
      "return_1d": "-0.07%",
      "return_30d": "2.83%",
      "return_1y": "14.26%",
      "cagr": "26.61%",
      "max_drawdown": "-42.80%",
      "beta": 1.1,
      "alpha": 0.07,
      "sharpe": 0.864,
      "win_rate": "65.39%",
      "avg_win": "0.96%",
      "avg_loss": "-0.90%",
      "volatility": "4.59%",
      "std_dev": 0.21,
      "info_ratio": 0.58,
      "treynor": 0.17,
      "trades": 2662,
      "description": "The Lobbying Spending Growth Strategy takes an equal-weighted position in 10 publicly-traded companies that disclosed the most Quarter over Quarter growth in U.S. federal lobbying expenditures, rebalanced monthly.",
      "source_url": "https://www.quiverquant.com/strategies/s/Lobbying Spending Growth/"
    },
    "Michael Burry": {
      "start_date": "2016-02-17",
      "return_1d": "1.00%",
      "return_30d": "6.99%",
      "return_1y": "73.71%",
      "cagr": "30.45%",
      "max_drawdown": "-52.10%",
      "beta": 0.83,
      "alpha": 0.16,
      "sharpe": 0.721,
      "win_rate": "71.34%",
      "avg_win": "1.63%",
      "avg_loss": "-1.01%",
      "volatility": "10.55%",
      "std_dev": 0.32,
      "info_ratio": 0.48,
      "treynor": 0.28,
      "trades": 652,
      "description": "The Michael Burry Strategy attempts to mirror the portfolio of Michael Burry's Scion Asset Management using 13F filings and is rebalanced when new filings are reported.",
      "source_url": "https://www.quiverquant.com/strategies/s/Michael Burry/"
    },
    "Nancy Pelosi": {
      "start_date": "2014-05-16",
      "return_1d": "-0.05%",
      "return_30d": "0.04%",
      "return_1y": "15.63%",
      "cagr": "21.06%",
      "max_drawdown": "-37.40%",
      "beta": 1.14,
      "alpha": 0.05,
      "sharpe": 0.733,
      "win_rate": "73.04%",
      "avg_win": "0.75%",
      "avg_loss": "-0.17%",
      "volatility": "3.46%",
      "std_dev": 0.19,
      "info_ratio": 0.63,
      "treynor": 0.12,
      "trades": 715,
      "description": "The Nancy Pelosi Strategy attempts to mirror the portfolio of common stock for Rep. Nancy Pelosi (and their family) and is rebalanced when new trades or annual reports are reported.",
      "source_url": "https://www.quiverquant.com/strategies/s/Nancy Pelosi/"
    },
    "Rob Bresnahan": {
      "start_date": "2025-06-01",
      "return_1d": "0.25%",
      "return_30d": "2.85%",
      "return_1y": "16.16%",
      "cagr": "26.60%",
      "max_drawdown": "-5.60%",
      "beta": 1.0,
      "alpha": -0.03,
      "sharpe": 1.352,
      "win_rate": "70.03%",
      "avg_win": "0.02%",
      "avg_loss": "-0.02%",
      "volatility": "0.89%",
      "std_dev": 0.09,
      "info_ratio": -0.73,
      "treynor": 0.13,
      "trades": 824,
      "description": "The Rob Bresnahan Strategy attempts to mirror the portfolio of common stock for Rep. Rob Bresnahan (and their family) and is rebalanced when new trades or annual reports are reported.",
      "source_url": "https://www.quiverquant.com/strategies/s/Rob Bresnahan/"
    },
    "Sector Weighted DC Insider": {
      "start_date": "2020-04-01",
      "return_1d": "0.53%",
      "return_30d": "3.45%",
      "return_1y": "26.77%",
      "cagr": "24.05%",
      "max_drawdown": "-18.70%",
      "beta": 0.83,
      "alpha": 0.04,
      "sharpe": 0.994,
      "win_rate": "84.26%",
      "avg_win": "0.39%",
      "avg_loss": "-0.25%",
      "volatility": "1.98%",
      "std_dev": 0.14,
      "info_ratio": 0.24,
      "treynor": 0.17,
      "trades": 910,
      "description": "The Sector Weighted DC Insider Strategy tracks the performance of companies with a significant amount of both corporate lobbying, government contracts, and congressional stock trading. The portfolio is rebalanced at the start of every month, and weighted to match S&P 500 sector allocation.",
      "source_url": "https://www.quiverquant.com/strategies/s/Sector Weighted DC Insider/"
    },
    "Sheldon Whitehouse": {
      "start_date": "2014-02-28",
      "return_1d": "0.70%",
      "return_30d": "2.26%",
      "return_1y": "25.37%",
      "cagr": "18.38%",
      "max_drawdown": "-30.60%",
      "beta": 1.07,
      "alpha": 0.03,
      "sharpe": 0.711,
      "win_rate": "80.94%",
      "avg_win": "0.07%",
      "avg_loss": "-0.03%",
      "volatility": "2.59%",
      "std_dev": 0.16,
      "info_ratio": 0.76,
      "treynor": 0.11,
      "trades": 6756,
      "description": "The Sheldon Whitehouse Strategy attempts to mirror the portfolio of common stock for Senator Sheldon Whitehouse (and their family) and is rebalanced when new trades or annual reports are reported.",
      "source_url": "https://www.quiverquant.com/strategies/s/Sheldon Whitehouse/"
    },
    "Shelley Moore Capito": {
      "start_date": "2014-05-16",
      "return_1d": "0.36%",
      "return_30d": "1.08%",
      "return_1y": "18.37%",
      "cagr": "10.59%",
      "max_drawdown": "-32.80%",
      "beta": 0.85,
      "alpha": -0.01,
      "sharpe": 0.435,
      "win_rate": "82.55%",
      "avg_win": "0.04%",
      "avg_loss": "-0.02%",
      "volatility": "1.70%",
      "std_dev": 0.13,
      "info_ratio": -0.5,
      "treynor": 0.07,
      "trades": 6425,
      "description": "The Shelley Moore Capito Strategy attempts to mirror the portfolio of common stock for Senator Shelley Moore Capito (and their family) and is rebalanced when new trades or annual reports are reported.",
      "source_url": "https://www.quiverquant.com/strategies/s/Shelley Moore Capito/"
    },
    "Tim Moore": {
      "start_date": "2025-06-01",
      "return_1d": "1.39%",
      "return_30d": "3.66%",
      "return_1y": "24.22%",
      "cagr": "38.51%",
      "max_drawdown": "-10.60%",
      "beta": 1.05,
      "alpha": 0.06,
      "sharpe": 1.206,
      "win_rate": "63.16%",
      "avg_win": "0.06%",
      "avg_loss": "-0.01%",
      "volatility": "3.29%",
      "std_dev": 0.18,
      "info_ratio": 0.42,
      "treynor": 0.21,
      "trades": 322,
      "description": "The Tim Moore Strategy attempts to mirror the portfolio of common stock for Rep. Tim Moore (and their family) and is rebalanced when new trades or annual reports are reported.",
      "source_url": "https://www.quiverquant.com/strategies/s/Tim Moore/"
    },
    "Tina Smith": {
      "start_date": "2019-01-01",
      "return_1d": "4.09%",
      "return_30d": "1.38%",
      "return_1y": "2.76%",
      "cagr": "8.95%",
      "max_drawdown": "-42.10%",
      "beta": 0.85,
      "alpha": -0.02,
      "sharpe": 0.272,
      "win_rate": "78.67%",
      "avg_win": "1.01%",
      "avg_loss": "-0.65%",
      "volatility": "3.68%",
      "std_dev": 0.19,
      "info_ratio": -0.3,
      "treynor": 0.06,
      "trades": 210,
      "description": "The Tina Smith Strategy attempts to mirror the portfolio of common stock for Senator Tina Smith (and their family) and is rebalanced when new trades or annual reports are reported.",
      "source_url": "https://www.quiverquant.com/strategies/s/Tina Smith/"
    },
    "Tom Carper": {
      "start_date": "2014-03-07",
      "return_1d": "0.15%",
      "return_30d": "2.54%",
      "return_1y": "32.64%",
      "cagr": "12.00%",
      "max_drawdown": "-40.30%",
      "beta": 0.99,
      "alpha": -0.01,
      "sharpe": 0.462,
      "win_rate": "76.29%",
      "avg_win": "0.04%",
      "avg_loss": "-0.03%",
      "volatility": "2.40%",
      "std_dev": 0.15,
      "info_ratio": -0.14,
      "treynor": 0.07,
      "trades": 6300,
      "description": "The Tom Carper Strategy attempts to mirror the portfolio of common stock for Senator Tom Carper (and their family) and is rebalanced when new trades or annual reports are reported.",
      "source_url": "https://www.quiverquant.com/strategies/s/Tom Carper/"
    },
    "Top Gov Contract Recipients": {
      "start_date": "2009-03-01",
      "return_1d": "0.13%",
      "return_30d": "13.63%",
      "return_1y": "18.68%",
      "cagr": "19.37%",
      "max_drawdown": "-41.20%",
      "beta": 0.86,
      "alpha": 0.04,
      "sharpe": 0.769,
      "win_rate": "71.14%",
      "avg_win": "0.31%",
      "avg_loss": "-0.18%",
      "volatility": "2.70%",
      "std_dev": 0.16,
      "info_ratio": 0.22,
      "treynor": 0.15,
      "trades": 3142,
      "description": "The Top Gov Contract Recipients Strategy selects the top 20 recipients of government contracts, weighted by the values of the announced contracts. Each company's government contracts are measured with an exponential moving average to favor more recent contracts, while still weighing historical contracts. This portfolio is rebalanced at the start of every month.",
      "source_url": "https://www.quiverquant.com/strategies/s/Top Gov Contract Recipients/"
    },
    "Top Lobbying Spenders": {
      "start_date": "2009-03-01",
      "return_1d": "-0.23%",
      "return_30d": "3.64%",
      "return_1y": "22.32%",
      "cagr": "16.67%",
      "max_drawdown": "-28.80%",
      "beta": 0.87,
      "alpha": 0.02,
      "sharpe": 0.736,
      "win_rate": "80.05%",
      "avg_win": "0.51%",
      "avg_loss": "-0.64%",
      "volatility": "2.02%",
      "std_dev": 0.14,
      "info_ratio": 0.03,
      "treynor": 0.12,
      "trades": 1813,
      "description": "The Top Lobbying Spenders Strategy takes an equal-weighted position in 10 publicly-traded companies that have reported the most lobbying spending over the last quarter, rebalanced monthly.",
      "source_url": "https://www.quiverquant.com/strategies/s/Top Lobbying Spenders/"
    },
    "Transportation and Infra. Committee (House)": {
      "start_date": "2020-04-01",
      "return_1d": "0.22%",
      "return_30d": "9.30%",
      "return_1y": "52.67%",
      "cagr": "33.96%",
      "max_drawdown": "-39.90%",
      "beta": 0.73,
      "alpha": 0.13,
      "sharpe": 1.104,
      "win_rate": "63.79%",
      "avg_win": "0.48%",
      "avg_loss": "-0.36%",
      "volatility": "3.79%",
      "std_dev": 0.19,
      "info_ratio": 0.56,
      "treynor": 0.29,
      "trades": 1900,
      "description": "The Transportation and Infra. Committee (House) Strategy tracks the performance of stocks that have been recently purchased by current/past members of the U.S. House's Transportation and Infrastructure Committee (or their family). This strategy is weighted based on the reported size of the purchases, with weekly rebalancing.",
      "source_url": "https://www.quiverquant.com/strategies/s/Transportation and Infra. Committee (House)/"
    },
    "U.S. House Long-Short": {
      "start_date": "2020-04-01",
      "return_1d": "0.16%",
      "return_30d": "1.97%",
      "return_1y": "36.35%",
      "cagr": "32.08%",
      "max_drawdown": "-24.30%",
      "beta": 1.06,
      "alpha": 0.08,
      "sharpe": 0.908,
      "win_rate": "53.90%",
      "avg_win": "0.30%",
      "avg_loss": "-0.20%",
      "volatility": "5.52%",
      "std_dev": 0.23,
      "info_ratio": 0.52,
      "treynor": 0.2,
      "trades": 5152,
      "description": "The U.S. House Long-Short Strategy tracks the performance of stocks that have been recently purchased or sold by members of the U.S. House (or their family). It takes a long position in stocks that have been purchased, and a short position in stocks which have been sold. This strategy is weighted based on the reported size of the transactions and employs leverage with 130% long exposure and 30% short exposure, with weekly rebalancing.",
      "source_url": "https://www.quiverquant.com/strategies/s/U.S. House Long-Short/"
    },
    "Wall Street Conviction": {
      "start_date": "2017-01-01",
      "return_1d": "-0.46%",
      "return_30d": "-0.45%",
      "return_1y": "16.32%",
      "cagr": "17.77%",
      "max_drawdown": "-30.40%",
      "beta": 1.01,
      "alpha": 0.02,
      "sharpe": 0.652,
      "win_rate": "86.09%",
      "avg_win": "0.55%",
      "avg_loss": "-0.85%",
      "volatility": "2.65%",
      "std_dev": 0.16,
      "info_ratio": 0.4,
      "treynor": 0.1,
      "trades": 638,
      "description": "The Wall Street Conviction Strategy uses 13F filings for institutions holdings over $100M in securities to find the stock that each fund has the highest conviction on within the S&P500 universe. Conviction here is measured as the percent allocation in their portfolio less the allocation in the S&P500. The highest-conviction stock for all funds are aggregated to form the equal-weighted selected stocks for this strategy. Positions are rebalanced quarterly, 47 days after the end of the previous quarter to allow time for funds to file. The basis of this strategy is detailed in the whitepaper: Systematic 13F Hedge Fund Alpha .",
      "source_url": "https://www.quiverquant.com/strategies/s/Wall Street Conviction/"
    }
  }
}